mktr/__init__.py
mktr/main.py
mktr-0.1.5.dist-info/licenses/LICENSE
mktr-0.1.5.dist-info/METADATA
mktr-0.1.5.dist-info/WHEEL
mktr-0.1.5.dist-info/entry_points.txt
mktr-0.1.5.dist-info/top_level.txt
mktr-0.1.5.dist-info/RECORD
